tabulardf/__init__.py
tabulardf/cli/__init__.py
tabulardf/cli/click_custom.py
tabulardf/cli/context_module.py
tabulardf/cli/converter_setup.py
tabulardf/cli/dataframe_utils.py
tabulardf/cli/docs.py
tabulardf/converters.py
tabulardf/tabulardf_types.py
tabulardf/tacl.py
tabulardf-0.1.1.dist-info/LICENSE
tabulardf-0.1.1.dist-info/METADATA
tabulardf-0.1.1.dist-info/WHEEL
tabulardf-0.1.1.dist-info/entry_points.txt
tabulardf-0.1.1.dist-info/RECORD
