Metadata-Version: 2.1
Name: tabulardf
Version: 0.1.1
Summary: 
Author: Lukas Plank
Author-email: lupl@tuta.io
Requires-Python: >=3.11,<4.0
Classifier: Programming Language :: Python :: 3
Classifier: Programming Language :: Python :: 3.11
Requires-Dist: click (>=8.1.6,<9.0.0)
Requires-Dist: jinja2 (>=3.1.2,<4.0.0)
Requires-Dist: lodkit (>=0.1.1,<0.2.0)
Requires-Dist: lxml (>=4.9.3,<5.0.0)
Requires-Dist: openpyxl (>=3.1.2,<4.0.0)
Requires-Dist: pandas (>=2.0.3,<3.0.0)
Requires-Dist: rdflib (>=7.0.0,<8.0.0)
